{"0": "Animal_Disturbance", "1": "Check_Report_Status", "2": "Complaint_Against_Officer", "3": "Compliment_Officer", "4": "Cybercrime_Report", "5": "Domestic_Violence_Report", "6": "Drug_Related_Inquiry", "7": "Emergency_Contact", "8": "Event_Security", "9": "File_Police_Report", "10": "Juvenile_Delinquency", "11": "Legal_Advice", "12": "Lost_And_Found", "13": "Missing_Person", "14": "Neighborhood_Watch", "15": "Parking_Violation", "16": "Permit_Application", "17": "Public_Records_Request", "18": "Report_Accident", "19": "Required_Documents_For_Report", "20": "Road_Closure_Information", "21": "Safety_Tips", "22": "Traffic_Fine_Payment", "23": "Witness_Statement", "24": "affirm", "25": "bot_challenge", "26": "deny", "27": "goodbye", "28": "greet", "29": "mood_great", "30": "mood_unhappy"}